aiosoma/__cli__.py
aiosoma/__init__.py
aiosoma/py.typed
aiosoma/soma_connect.py
aiosoma/soma_shade.py
aiosoma-1.1.25.dist-info/LICENSE
aiosoma-1.1.25.dist-info/METADATA
aiosoma-1.1.25.dist-info/WHEEL
aiosoma-1.1.25.dist-info/entry_points.txt
aiosoma-1.1.25.dist-info/RECORD
