Metadata-Version: 2.1
Name: aiosoma
Version: 1.1.25
Summary: Asyncio SOMA Connect
Home-page: https://github.com/Djelibeybi/aiosoma
License: MIT
Author: Avi Miller
Author-email: me@dje.li
Requires-Python: >=3.11,<4.0
Classifier: Development Status :: 4 - Beta
Classifier: Intended Audience :: Developers
Classifier: License :: OSI Approved :: MIT License
Classifier: Natural Language :: English
Classifier: Operating System :: OS Independent
Classifier: Programming Language :: Python :: 3
Classifier: Programming Language :: Python :: 3.11
Classifier: Programming Language :: Python :: 3.12
Classifier: Topic :: Home Automation
Classifier: Topic :: Software Development :: Libraries
Classifier: Typing :: Typed
Requires-Dist: aiohttp (>=3.9.1,<4.0.0)
Requires-Dist: backoff (>=2.2.1,<3.0.0)
Requires-Dist: black (==24.2.0)
Requires-Dist: pre-commit (==3.6.2)
Requires-Dist: rich (>=13.0.0,<14.0.0)
Project-URL: Bug Tracker, https://github.com/Djelibeybi/aiosoma/issues
Project-URL: Changelog, https://github.com/Djelibeybi/aiosoma/blob/main/CHANGELOG.md
Project-URL: Documentation, https://aiosoma.readthedocs.io
Project-URL: Repository, https://github.com/Djelibeybi/aiosoma
